[
  {
    "feature":"interest_overlap",
    "importance":0.9806222868
  },
  {
    "feature":"review_count",
    "importance":0.0085778602
  },
  {
    "feature":"dist_km",
    "importance":0.0031341332
  },
  {
    "feature":"cat_nature",
    "importance":0.0012249035
  },
  {
    "feature":"cat_culture",
    "importance":0.0010783886
  },
  {
    "feature":"cat_history",
    "importance":0.000810904
  },
  {
    "feature":"outdoor",
    "importance":0.0004936558
  },
  {
    "feature":"cat_Bed & Breakfast",
    "importance":0.0004359081
  },
  {
    "feature":"cat_Hotels & Travel",
    "importance":0.0003807191
  },
  {
    "feature":"user_needs_hotel",
    "importance":0.0002545844
  },
  {
    "feature":"user_group_amigos",
    "importance":0.0002353644
  },
  {
    "feature":"user_group_solo",
    "importance":0.0002119261
  },
  {
    "feature":"is_romantic",
    "importance":0.0002101901
  },
  {
    "feature":"cat_Mexican",
    "importance":0.0001938226
  },
  {
    "feature":"cat_bar",
    "importance":0.0001849628
  },
  {
    "feature":"is_accessible",
    "importance":0.0001446225
  },
  {
    "feature":"cat_local food",
    "importance":0.00014422
  },
  {
    "feature":"cat_gastronomy",
    "importance":0.0001274784
  },
  {
    "feature":"cat_Hotels",
    "importance":0.0001223522
  },
  {
    "feature":"romantic_match",
    "importance":0.0001088158
  },
  {
    "feature":"user_tur_rural",
    "importance":0.0000949142
  },
  {
    "feature":"user_group_pareja",
    "importance":0.0000879878
  },
  {
    "feature":"cat_Hiking",
    "importance":0.0000842531
  },
  {
    "feature":"cat_Restaurants",
    "importance":0.0000800849
  },
  {
    "feature":"cat_park",
    "importance":0.0000788823
  },
  {
    "feature":"user_tur_gastronomico",
    "importance":0.0000719642
  },
  {
    "feature":"cat_coffee",
    "importance":0.000058043
  },
  {
    "feature":"user_tur_aventura",
    "importance":0.0000557285
  },
  {
    "feature":"is_good_for_kids",
    "importance":0.0000517552
  },
  {
    "feature":"cat_Tours",
    "importance":0.0000507262
  },
  {
    "feature":"kids_match",
    "importance":0.0000497524
  },
  {
    "feature":"cat_volcano",
    "importance":0.0000467771
  },
  {
    "feature":"cat_monument",
    "importance":0.0000410482
  },
  {
    "feature":"user_pref_outdoor",
    "importance":0.000037048
  },
  {
    "feature":"user_tur_naturaleza",
    "importance":0.0000326682
  },
  {
    "feature":"cat_museum",
    "importance":0.0000280673
  },
  {
    "feature":"cat_Landmarks & Historical Buildings",
    "importance":0.0000279527
  },
  {
    "feature":"cat_food",
    "importance":0.0000277583
  },
  {
    "feature":"user_budget",
    "importance":0.0000271512
  },
  {
    "feature":"user_group_familia",
    "importance":0.0000261461
  },
  {
    "feature":"price_level",
    "importance":0.000025314
  },
  {
    "feature":"user_pref_food",
    "importance":0.0000229959
  },
  {
    "feature":"cat_Arts & Entertainment",
    "importance":0.0000184793
  },
  {
    "feature":"user_tur_cultural",
    "importance":0.0000183343
  },
  {
    "feature":"cat_Parks",
    "importance":0.0000170016
  },
  {
    "feature":"cat_market",
    "importance":0.0000169118
  },
  {
    "feature":"cat_viewpoint",
    "importance":0.0000154947
  },
  {
    "feature":"cat_Museums",
    "importance":0.0000151844
  },
  {
    "feature":"cat_botanical garden",
    "importance":0.0000134921
  },
  {
    "feature":"cat_restaurant",
    "importance":0.0000118858
  },
  {
    "feature":"cat_Active Life",
    "importance":0.000011298
  },
  {
    "feature":"user_wants_tours",
    "importance":0.0000093013
  },
  {
    "feature":"cat_Cafes",
    "importance":0.0000090836
  },
  {
    "feature":"cat_waterfall",
    "importance":0.0000084311
  },
  {
    "feature":"cat_mountain",
    "importance":0.0000076943
  },
  {
    "feature":"cat_hacienda",
    "importance":0.0000066235
  },
  {
    "feature":"cat_Food",
    "importance":0.0000058716
  },
  {
    "feature":"tours_match",
    "importance":0.0000058644
  },
  {
    "feature":"cat_zocalo",
    "importance":0.0000028128
  },
  {
    "feature":"cat_cathedral",
    "importance":0.0000012278
  },
  {
    "feature":"cat_Zoos",
    "importance":0.0000006637
  },
  {
    "feature":"budget_delta",
    "importance":0.0000002266
  },
  {
    "feature":"is_open",
    "importance":0.0
  },
  {
    "feature":"cat_Botanical Gardens",
    "importance":0.0
  },
  {
    "feature":"cat_Campgrounds",
    "importance":0.0
  },
  {
    "feature":"user_age_range",
    "importance":0.0
  },
  {
    "feature":"cat_sanctuary",
    "importance":0.0
  },
  {
    "feature":"user_requires_accessibility",
    "importance":0.0
  },
  {
    "feature":"user_has_visited_region",
    "importance":0.0
  }
]